LT/MCA.py
LT/__init__.py
LT/box.py
LT/datafile.py
LT/get_precision.py
LT/parameterfile.py
LT/pdatafile.py
LT/plotting.py
LT_Fit/__init__.py
LT_Fit/gen_fit.py
LT_Fit/linear_fit.py
LT_Fit/parameters.py
labtools3-1.1.3.21.dist-info/licenses/LICENSE
labtools3-1.1.3.21.dist-info/METADATA
labtools3-1.1.3.21.dist-info/WHEEL
labtools3-1.1.3.21.dist-info/top_level.txt
labtools3-1.1.3.21.dist-info/RECORD
