Metadata-Version: 2.4
Name: LabTools3
Version: 1.1.3.21
Summary: Python 3 Package of modules for typical analysis tasks analyzing physics data
Home-page: http://wanda.fiu.edu/LabTools3
Author: Werner Boeglin
Author-email: boeglinw@fiu.edu
License: MIT
Keywords: Data Analysis
Classifier: Programming Language :: Python :: 3.8
Requires-Python: >=3.8
License-File: LICENSE
Dynamic: author
Dynamic: author-email
Dynamic: classifier
Dynamic: description
Dynamic: description-content-type
Dynamic: home-page
Dynamic: keywords
Dynamic: license
Dynamic: license-file
Dynamic: requires-python
Dynamic: summary
